template_tool/__init__.py
template_tool/__main__.py
template_tool/actions/__init__.py
template_tool/actions/list.py
template_tool/actions/load.py
template_tool/actions/remove.py
template_tool/actions/save.py
template_tool/colorization/__init__.py
template_tool-0.1.6.dist-info/METADATA
template_tool-0.1.6.dist-info/WHEEL
template_tool-0.1.6.dist-info/top_level.txt
template_tool-0.1.6.dist-info/RECORD
